nibabies_wrapper.py
python3.9/site-packages/_virtualenv.pth
python3.9/site-packages/_virtualenv.py
python3.9/site-packages/distutils-precedence.pth
python3.9/site-packages/setuptools-57.4.0.virtualenv
python3.9/site-packages/wheel-0.37.0.virtualenv
python3.9/site-packages/__pycache__/_virtualenv.cpython-39.pyc
python3.9/site-packages/_distutils_hack/__init__.py
python3.9/site-packages/_distutils_hack/override.py
python3.9/site-packages/_distutils_hack/__pycache__/__init__.cpython-39.pyc
python3.9/site-packages/_distutils_hack/__pycache__/override.cpython-39.pyc
python3.9/site-packages/pip/__init__.py
python3.9/site-packages/pip/__main__.py
python3.9/site-packages/pip/py.typed
python3.9/site-packages/pip/__pycache__/__init__.cpython-39.pyc
python3.9/site-packages/pip/__pycache__/__main__.cpython-39.pyc
python3.9/site-packages/pip/_internal/__init__.py
python3.9/site-packages/pip/_internal/build_env.py
python3.9/site-packages/pip/_internal/cache.py
python3.9/site-packages/pip/_internal/configuration.py
python3.9/site-packages/pip/_internal/exceptions.py
python3.9/site-packages/pip/_internal/main.py
python3.9/site-packages/pip/_internal/pyproject.py
python3.9/site-packages/pip/_internal/self_outdated_check.py
python3.9/site-packages/pip/_internal/wheel_builder.py
python3.9/site-packages/pip/_internal/__pycache__/__init__.cpython-39.pyc
python3.9/site-packages/pip/_internal/__pycache__/build_env.cpython-39.pyc
python3.9/site-packages/pip/_internal/__pycache__/cache.cpython-39.pyc
python3.9/site-packages/pip/_internal/__pycache__/configuration.cpython-39.pyc
python3.9/site-packages/pip/_internal/__pycache__/exceptions.cpython-39.pyc
python3.9/site-packages/pip/_internal/__pycache__/main.cpython-39.pyc
python3.9/site-packages/pip/_internal/__pycache__/pyproject.cpython-39.pyc
python3.9/site-packages/pip/_internal/__pycache__/self_outdated_check.cpython-39.pyc
python3.9/site-packages/pip/_internal/__pycache__/wheel_builder.cpython-39.pyc
nibabies_wrapper-99.99.99.dist-info/METADATA
nibabies_wrapper-99.99.99.dist-info/WHEEL
nibabies_wrapper-99.99.99.dist-info/entry_points.txt
nibabies_wrapper-99.99.99.dist-info/top_level.txt
python3.9/site-packages/pip-21.2.4.dist-info/INSTALLER
python3.9/site-packages/pip-21.2.4.dist-info/LICENSE.txt
python3.9/site-packages/pip-21.2.4.dist-info/METADATA
python3.9/site-packages/pip-21.2.4.dist-info/RECORD
python3.9/site-packages/pip-21.2.4.dist-info/REQUESTED
python3.9/site-packages/pip-21.2.4.dist-info/WHEEL
python3.9/site-packages/pip-21.2.4.dist-info/entry_points.txt
python3.9/site-packages/pip-21.2.4.dist-info/top_level.txt
python3.9/site-packages/setuptools-57.4.0.dist-info/INSTALLER
python3.9/site-packages/setuptools-57.4.0.dist-info/LICENSE
python3.9/site-packages/setuptools-57.4.0.dist-info/METADATA
python3.9/site-packages/setuptools-57.4.0.dist-info/RECORD
python3.9/site-packages/setuptools-57.4.0.dist-info/WHEEL
python3.9/site-packages/setuptools-57.4.0.dist-info/entry_points.txt
python3.9/site-packages/setuptools-57.4.0.dist-info/top_level.txt
python3.9/site-packages/wheel-0.37.0.dist-info/INSTALLER
python3.9/site-packages/wheel-0.37.0.dist-info/LICENSE.txt
python3.9/site-packages/wheel-0.37.0.dist-info/METADATA
python3.9/site-packages/wheel-0.37.0.dist-info/RECORD
python3.9/site-packages/wheel-0.37.0.dist-info/WHEEL
python3.9/site-packages/wheel-0.37.0.dist-info/entry_points.txt
python3.9/site-packages/wheel-0.37.0.dist-info/top_level.txt
nibabies_wrapper-99.99.99.dist-info/RECORD
