Metadata-Version: 2.1
Name: nibabies-wrapper
Version: 99.99.99
Summary: A wrapper for generating Docker and Singularity commands for simpler NiBabies usage
Home-page: https://github.com/nipreps/nibabies
Author: The NiPreps developers
Author-email: nipreps@gmail.com
Maintainer: Mathias Goncalves
Maintainer-email: nipreps@gmail.com
License: Apache 2.0
Platform: UNKNOWN
Classifier: Development Status :: 4 - Beta
Classifier: Intended Audience :: Science/Research
Classifier: License :: OSI Approved :: BSD License
Classifier: Programming Language :: Python :: 2.7
Classifier: Programming Language :: Python :: 3.7
Classifier: Programming Language :: Python :: 3.8
Classifier: Programming Language :: Python :: 3.9
Requires-Dist: setuptools (<45) ; python_version < "3.0"
